lfr/__init__.py
lfr/antlrgen/__init__.py
lfr/antlrgen/lfrX.interp
lfr/antlrgen/lfrX.tokens
lfr/antlrgen/lfrXLexer.interp
lfr/antlrgen/lfrXLexer.py
lfr/antlrgen/lfrXLexer.tokens
lfr/antlrgen/lfrXListener.py
lfr/antlrgen/lfrXParser.py
lfr/antlrgen/lfrXVisitor.py
lfr/cmdline.py
lfr/compiler/__init__.py
lfr/compiler/constraints/performanceconstraint.py
lfr/compiler/distribute/BitVector.py
lfr/compiler/distribute/__init__.py
lfr/compiler/distribute/distributeblock.py
lfr/compiler/distribute/statetable.py
lfr/compiler/language/__init__.py
lfr/compiler/language/concatenation.py
lfr/compiler/language/fluidexpression.py
lfr/compiler/language/logicexpressions.py
lfr/compiler/language/operation.py
lfr/compiler/language/utils.py
lfr/compiler/language/vector.py
lfr/compiler/language/vectorrange.py
lfr/compiler/lfrerror.py
lfr/compiler/module.py
lfr/compiler/moduleio.py
lfr/distBlockListener.py
lfr/fig/__init__.py
lfr/fig/fignode.py
lfr/fig/fluidinteractiongraph.py
lfr/fig/interaction.py
lfr/lfrbaseListener.py
lfr/mappingCompiler.py
lfr/moduleinstanceListener.py
lfr/netlistgenerator/__init__.py
lfr/netlistgenerator/dafdadapter.py
lfr/netlistgenerator/explicitmapping.py
lfr/netlistgenerator/mappinglibrary.py
lfr/netlistgenerator/namegenerator.py
lfr/netlistgenerator/netlistsizor.py
lfr/netlistgenerator/primitive.py
lfr/netlistgenerator/technologymapper.py
lfr/netlistgenerator/v2/__init__.py
lfr/netlistgenerator/v2/connectingoption.py
lfr/netlistgenerator/v2/constructiongraph.py
lfr/netlistgenerator/v2/constructionnode.py
lfr/netlistgenerator/v2/gen_strategies/dropx.py
lfr/netlistgenerator/v2/gen_strategies/dummy.py
lfr/netlistgenerator/v2/gen_strategies/genstrategy.py
lfr/netlistgenerator/v2/gen_strategies/mars.py
lfr/netlistgenerator/v2/generator.py
lfr/netlistgenerator/v2/mappingoption.py
lfr/netlistgenerator/v2/networkmappingoption.py
lfr/parameters.py
lfr/preprocessor.py
lfr/utils.py
lfr-0.1.4.dist-info/entry_points.txt
lfr-0.1.4.dist-info/WHEEL
lfr-0.1.4.dist-info/METADATA
lfr-0.1.4.dist-info/RECORD
