Metadata-Version: 2.1
Name: lfr
Version: 0.1.4
Summary: 
License: BSD-3-Clause
Author: Radhakrishna Sanka
Author-email: rkrishnasanka@gmail.com
Requires-Python: >=3.8,<4.0
Classifier: License :: OSI Approved :: BSD License
Classifier: Programming Language :: Python :: 3
Classifier: Programming Language :: Python :: 3.8
Classifier: Programming Language :: Python :: 3.9
Requires-Dist: antlr4-python3-runtime (>=4.8,<5.0)
Requires-Dist: argparse (>=1.4.0,<2.0.0)
Requires-Dist: networkx (>=2.5,<3.0)
Requires-Dist: pygraphviz (>=1.6,<2.0)
Requires-Dist: pymint (>=0.1.3,<0.2.0)
